flatpaker/__init__.py
flatpaker/config.py
flatpaker/description.py
flatpaker/entry.py
flatpaker/util.py
flatpaker/actions/build_flatpak.py
flatpaker/actions/build_runtime.py
flatpaker/actions/generate.py
flatpaker/data/com.github.dcbaker.flatpaker.RPGM.Platform.yml
flatpaker/data/com.github.dcbaker.flatpaker.RenPy.7.py2.Sdk.yml
flatpaker/data/com.github.dcbaker.flatpaker.RenPy.7.py3.Sdk.yml
flatpaker/data/com.github.dcbaker.flatpaker.RenPy.8.Sdk.yml
flatpaker/data/files/00enabledebug.rpy
flatpaker/data/files/renpy.py
flatpaker/data/modules/python-2.7.json
flatpaker/data/modules/python2-requirements.json
flatpaker/data/modules/python3-cython0.yml
flatpaker/data/modules/python3-requirements.json
flatpaker/data/modules/renpy-shared.yml
flatpaker/data/patches/pygame-sdl2-7-install-headers.patch
flatpaker/data/patches/pygame-sdl2-7-remove-pathlib.patch
flatpaker/data/patches/pygame-sdl2-7-use-correct-cython.patch
flatpaker/data/patches/pygame-sdl2-fix-header-install-path.patch
flatpaker/data/patches/renpy-7-fix-styles-dirname.patch
flatpaker/data/patches/renpy-ffmpeg-7.patch
flatpaker/data/patches/renpy-setuplib-fix-paths.patch
flatpaker/impl/__init__.py
flatpaker/impl/renpy.py
flatpaker/impl/rpgmaker.py
flatpaker-0.0.10.dist-info/entry_points.txt
flatpaker-0.0.10.dist-info/licenses/LICENSE
flatpaker-0.0.10.dist-info/WHEEL
flatpaker-0.0.10.dist-info/METADATA
flatpaker-0.0.10.dist-info/RECORD
