Metadata-Version: 2.4
Name: flatpaker
Version: 0.0.10
Summary: Utilities to convert various kinds of native binaries into flatpaks.
Keywords: flatpak,renpy,rpgmaker
Author-email: Dylan Baker <dylan@pnwbakers.com>
Requires-Python: >=3.9
Classifier: Development Status :: 3 - Alpha
Classifier: Environment :: Console
Classifier: License :: OSI Approved :: MIT License
Classifier: Programming Language :: Python :: 3 :: Only
Classifier: Programming Language :: Python :: 3.9
Classifier: Programming Language :: Python :: 3.10
Classifier: Programming Language :: Python :: 3.11
Classifier: Programming Language :: Python :: 3.12
Classifier: Programming Language :: Python :: 3.13
Classifier: Topic :: System :: Archiving :: Packaging
License-File: LICENSE
Requires-Dist: tomlkit
Project-URL: Issues, https://github.com/dcbaker/flatpaker/issues
Project-URL: Repository, https://github.com/dcbaker/flatpaker
